metrotransit/__init__.py
metrotransit/api/__init__.py
metrotransit/api/nex_trip/__init__.py
metrotransit/api/nex_trip/get_nextrip_agencies.py
metrotransit/api/nex_trip/get_nextrip_directions_route_id.py
metrotransit/api/nex_trip/get_nextrip_route_id_direction_id_place_code.py
metrotransit/api/nex_trip/get_nextrip_routes.py
metrotransit/api/nex_trip/get_nextrip_stop_id.py
metrotransit/api/nex_trip/get_nextrip_stopid_street.py
metrotransit/api/nex_trip/get_nextrip_stops_route_id_direction_id.py
metrotransit/api/nex_trip/get_nextrip_vehicles_route_id.py
metrotransit/client.py
metrotransit/errors.py
metrotransit/models/__init__.py
metrotransit/models/agency.py
metrotransit/models/alert_message.py
metrotransit/models/departure.py
metrotransit/models/direction.py
metrotransit/models/nex_trip_result.py
metrotransit/models/place.py
metrotransit/models/problem_details.py
metrotransit/models/route.py
metrotransit/models/stop.py
metrotransit/models/street_stop_response.py
metrotransit/models/vehicle.py
metrotransit/py.typed
metrotransit/types.py
metrotransit-0.1.2.dist-info/licenses/LICENSE
metrotransit-0.1.2.dist-info/WHEEL
metrotransit-0.1.2.dist-info/METADATA
metrotransit-0.1.2.dist-info/RECORD
