Metadata-Version: 2.4
Name: metrotransit
Version: 0.1.2
Summary: Tools for accessing Metro Transit data
Author: Ben Soyka
Author-email: Ben Soyka <hello@bsoyka.me>
License-Expression: MIT
License-File: LICENSE
Classifier: Development Status :: 4 - Beta
Classifier: Intended Audience :: Developers
Classifier: License :: OSI Approved :: MIT License
Classifier: Natural Language :: English
Classifier: Operating System :: OS Independent
Classifier: Programming Language :: Python
Classifier: Programming Language :: Python :: 3
Classifier: Programming Language :: Python :: 3 :: Only
Classifier: Programming Language :: Python :: 3.10
Classifier: Programming Language :: Python :: 3.11
Classifier: Programming Language :: Python :: 3.12
Classifier: Programming Language :: Python :: 3.13
Classifier: Programming Language :: Python :: 3.14
Classifier: Typing :: Typed
Requires-Dist: httpx>=0.23.0,<0.29.0
Requires-Dist: attrs>=25.4.0
Requires-Dist: python-dateutil>=2.8.0,<3.0.0
Requires-Dist: typing-extensions>=4.0.0,<5.0.0
Requires-Python: >=3.10
Project-URL: Changelog, https://github.com/bsoyka/metrotransit-py/releases
Project-URL: Sponsor, https://github.com/sponsors/bsoyka
